{
  "training": [
    {
      "activity": "Spring så långt du orkar. Gå tillbaka."
    },
    {
      "activity": "Gör 20 stycken armhävningar."
    },
    {
      "activity": "Gör plankan i 1 minut."
    },
    {
      "activity": "Cykla i skogen i 20 minuter."
    },
    {
      "activity": "Hoppa hopprep i 5 minuter."
    },
    {
      "activity": "Rocka rockring så länge du orkar."
    },
    {
      "activity": "Yoga i 20 minuter."
    },
    {
      "activity": "Meditera i 10 minuter."
    }
  ]
}